README.md
setup.py
ocean/__init__.py
ocean/main.py
ocean/classes/OceanDependencyModule.py
ocean/classes/OceanDropletModule.py
ocean/classes/OceanHandlerModule.py
ocean_pentest.egg-info/PKG-INFO
ocean_pentest.egg-info/SOURCES.txt
ocean_pentest.egg-info/dependency_links.txt
ocean_pentest.egg-info/entry_points.txt
ocean_pentest.egg-info/requires.txt
ocean_pentest.egg-info/top_level.txt