Metadata-Version: 2.1
Name: ocean-pentest
Version: 0.3
Summary: Automates many tasks for pentesting with the Digital Ocean Cloud Platform.
Home-page: https://github.com/scott-m-willett/ocean
Author: Scott Willett
Author-email: swillett@protonmail.com
License: UNKNOWN
Download-URL: https://github.com/scott-m-willett/ocean/archive/refs/tags/v0.2-alpha.tar.gz
Platform: UNKNOWN
Classifier: Programming Language :: Python :: 3
Classifier: License :: OSI Approved :: MIT License
Classifier: Operating System :: OS Independent
